[
    {
        "name": "TVS Apache RTR 160",
        "brand": "TVS",
        "kilometers": 7468,
        "ownerShipSerial": "1st",
        "price": 1412.45,
        "img": "https://fastly-production.24c.in/inspection-bike/appointments/spincar/prod/IN/IN_BIKE_1007195669/POST_REFURB/1632033471478/cu-0.jpg?w=350&h=auto&auto=format",
        "ratings": {
            "rate": 4.5,
            "raters": 25
        }
    },
    {
        "name": "TVS Apache RTR 200 4v",
        "brand": "TVS",
        "kilometers": 21674,
        "ownerShipSerial": "2nd",
        "price": 995.44,
        "img": "https://fastly-production.24c.in/inspection-bike/appointments/spincar/prod/IN/IN_BIKE_3089549885/POST_REFURB/1633251676925/cu-0.jpg?w=350&h=auto&auto=format",
        "ratings": {
            "rate": 4.2,
            "raters": 16
        }
    },
    {
        "name": "KTM Duke 200",
        "brand": "KTM",
        "kilometers": 18937,
        "ownerShipSerial": "1st",
        "price": 1532.45,
        "img": "https://fastly-production.24c.in/inspection-bike/appointments/spincar/prod/IN/IN_BIKE_1125607263/POST_REFURB/1628567311722/cu-0.jpg?w=260&h=188&auto=format",
        "ratings": {
            "rate": 3.2,
            "raters": 18
        }
    },
    {
        "name": "Hero HF Delux",
        "brand": "Hero",
        "kilometers": 31412,
        "ownerShipSerial": ">=3rd",
        "price": 400,
        "img": "https://fastly-production.24c.in/inspection-bike/appointments/spincar/prod/IN/IN_BIKE_4098952287/POST_REFURB/1633691165126/cu-0.jpg?w=260&h=188&auto=format",
        "ratings": {
            "rate": 4.9,
            "raters": 11
        }
    },
    {
        "name": "Bajaj Avenger Cruise 220",
        "brand": "Bajaj",
        "kilometers": 16865,
        "ownerShipSerial": "1st",
        "price": 730,
        "img": "https://fastly-production.24c.in/inspection-bike/appointments/spincar/prod/IN/IN_BIKE_1120451361/POST_REFURB/1627495357208/cu-0.jpg?w=260&h=188&auto=format",
        "ratings": {
            "rate": 3.2,
            "raters": 86
        }
    },
    {
        "name": "Aprilia Storm 125",
        "brand": "Aprilia",
        "kilometers": 15732,
        "ownerShipSerial": "1st",
        "price": 750,
        "img": "https://fastly-production.24c.in/inspection-bike/appointments/spincar/prod/IN/IN_BIKE_1122645061/POST_REFURB/1630918355197/cu-0.jpg?w=260&h=188&auto=format",
        "ratings": {
            "rate": 4.2,
            "raters": 19
        }
    },
    {
        "name": "TVS Apache RTR 160",
        "brand": "TVS",
        "kilometers": 7468,
        "ownerShipSerial": "1st",
        "price": 1412.45,
        "img": "https://fastly-production.24c.in/inspection-bike/appointments/spincar/prod/IN/IN_BIKE_1007195669/POST_REFURB/1632033471478/cu-0.jpg",
        "ratings": {
            "rate": 4.5,
            "raters": 25
        }
    },
    {
        "name": "TVS Apache RTR 160",
        "brand": "TVS",
        "kilometers": 7468,
        "ownerShipSerial": "1st",
        "price": 1412.45,
        "img": "https://fastly-production.24c.in/inspection-bike/appointments/spincar/prod/IN/IN_BIKE_1007195669/POST_REFURB/1632033471478/cu-0.jpg",
        "ratings": {
            "rate": 4.5,
            "raters": 25
        }
    },
    {
        "name": "TVS Apache RTR 160",
        "brand": "TVS",
        "kilometers": 7468,
        "ownerShipSerial": "1st",
        "price": 1412.45,
        "img": "https://fastly-production.24c.in/inspection-bike/appointments/spincar/prod/IN/IN_BIKE_1007195669/POST_REFURB/1632033471478/cu-0.jpg",
        "ratings": {
            "rate": 4.5,
            "raters": 25
        }
    },
    {
        "name": "TVS Apache RTR 160",
        "brand": "TVS",
        "kilometers": 7468,
        "ownerShipSerial": "1st",
        "price": 1412.45,
        "img": "https://fastly-production.24c.in/inspection-bike/appointments/spincar/prod/IN/IN_BIKE_1007195669/POST_REFURB/1632033471478/cu-0.jpg",
        "ratings": {
            "rate": 4.5,
            "raters": 25
        }
    },
    {
        "name": "TVS Apache RTR 160",
        "brand": "TVS",
        "kilometers": 7468,
        "ownerShipSerial": "1st",
        "price": 1412.45,
        "img": "https://fastly-production.24c.in/inspection-bike/appointments/spincar/prod/IN/IN_BIKE_1007195669/POST_REFURB/1632033471478/cu-0.jpg",
        "ratings": {
            "rate": 4.5,
            "raters": 25
        }
    },
    {
        "name": "TVS Apache RTR 160",
        "brand": "TVS",
        "kilometers": 7468,
        "ownerShipSerial": "1st",
        "price": 1412.45,
        "img": "https://fastly-production.24c.in/inspection-bike/appointments/spincar/prod/IN/IN_BIKE_1007195669/POST_REFURB/1632033471478/cu-0.jpg",
        "ratings": {
            "rate": 4.5,
            "raters": 25
        }
    }
]